grpc-stubs/__init__.pyi
grpc-stubs/py.typed
grpc-stubs/aio/__init__.pyi
grpc-stubs/aio/py.typed
grpc_channelz-stubs/__init__.pyi
grpc_channelz-stubs/py.typed
grpc_channelz-stubs/v1/__init__.pyi
grpc_channelz-stubs/v1/_servicer.pyi
grpc_channelz-stubs/v1/channelz.pyi
grpc_health-stubs/__init__.pyi
grpc_health-stubs/py.typed
grpc_health-stubs/v1/__init__.pyi
grpc_health-stubs/v1/health.pyi
grpc_reflection-stubs/__init__.pyi
grpc_reflection-stubs/py.typed
grpc_reflection-stubs/v1alpha/__init__.pyi
grpc_reflection-stubs/v1alpha/reflection.pyi
grpc_status-stubs/__init__.pyi
grpc_status-stubs/py.typed
grpc_status-stubs/rpc_status.pyi
grpc_stubs-1.53.0.5.dist-info/LICENSE
grpc_stubs-1.53.0.5.dist-info/METADATA
grpc_stubs-1.53.0.5.dist-info/WHEEL
grpc_stubs-1.53.0.5.dist-info/top_level.txt
grpc_stubs-1.53.0.5.dist-info/RECORD
