Metadata-Version: 2.1
Name: grpc-stubs
Version: 1.53.0.5
Summary: Mypy stubs for gRPC
Home-page: https://github.com/shabbyrobe/grpc-stubs
Author: Blake Williams
Author-email: code@shabbyrobe.org
License: MIT
Platform: UNKNOWN
Classifier: Development Status :: 3 - Alpha
Classifier: License :: OSI Approved :: MIT License
Classifier: Programming Language :: Python :: 3.6
Classifier: Programming Language :: Python :: 3.7
Classifier: Programming Language :: Python :: 3.8
Requires-Python: >=3.6
License-File: LICENSE
